trustcaptcha/__init__.py
trustcaptcha/captcha_manager.py
trustcaptcha/model/__init__.py
trustcaptcha/model/verification_result.py
trustcaptcha/model/verification_token.py
trustcaptcha-2.0.1.dist-info/licenses/LICENSE.md
trustcaptcha-2.0.1.dist-info/METADATA
trustcaptcha-2.0.1.dist-info/WHEEL
trustcaptcha-2.0.1.dist-info/entry_points.txt
trustcaptcha-2.0.1.dist-info/top_level.txt
trustcaptcha-2.0.1.dist-info/RECORD
