Metadata-Version: 2.4
Name: trustcaptcha
Version: 2.0.1
Summary: TrustCaptcha – Privacy-first CAPTCHA solution for Python. GDPR-compliant, bot protection made in Europe.
Author-email: TrustComponent <mail@trustcomponent.com>
License: Apache-2.0
Project-URL: Homepage, https://www.trustcomponent.com/en/products/captcha/integrations/python-captcha
Project-URL: Repository, https://github.com/trustcomponent/trustcaptcha-python
Keywords: captcha,bot-protection,bot-detection,gdpr,privacy,trustcaptcha,made-in-europe
License-File: LICENSE.md
Requires-Dist: requests
Requires-Dist: numpy
Provides-Extra: dev
Requires-Dist: pytest; extra == "dev"
Requires-Dist: flake8; extra == "dev"
Dynamic: license-file
